Ecarx_smart_project/__init__.py
Ecarx_smart_project/base_function.py
Ecarx_smart_project/canoe.py
Ecarx_smart_project/read_config.py
Ecarx_smart_project-1.0.dist-info/METADATA
Ecarx_smart_project-1.0.dist-info/WHEEL
Ecarx_smart_project-1.0.dist-info/top_level.txt
Ecarx_smart_project-1.0.dist-info/RECORD
